fs_mapping_tools/__init__.py
fs_mapping_tools/config.py
fs_mapping_tools/track/__init__.py
fs_mapping_tools/track/cones.py
fs_mapping_tools/vehicle/__init__.py
fs_mapping_tools/vehicle/car.py
fs_mapping_tools/vehicle/detection.py
fs_mapping_tools-0.2.0.dist-info/LICENSE
fs_mapping_tools-0.2.0.dist-info/METADATA
fs_mapping_tools-0.2.0.dist-info/WHEEL
fs_mapping_tools-0.2.0.dist-info/top_level.txt
fs_mapping_tools-0.2.0.dist-info/RECORD
