Metadata-Version: 2.1
Name: fs-mapping-tools
Version: 0.2.0
Summary: A set of simple utilities for track mapping, designed for Formula Student autonomous events.
Author-email: Paulo Sanchez <dev.szblzpaulo@gmail.com>
Maintainer-email: Paulo Sanchez <dev.szblzpaulo@gmail.com>
License: GNU AFFERO GENERAL PUBLIC LICENSE
Project-URL: Homepage, https://github.com/erlete/fs-mapping-tools
Project-URL: Bug Tracker, https://github.com/erlete/fs-mapping-tools/issues
Classifier: Development Status :: 4 - Beta
Classifier: Intended Audience :: Developers
Classifier: Intended Audience :: Education
Classifier: Intended Audience :: Science/Research
Classifier: License :: OSI Approved :: GNU General Public License v3 (GPLv3)
Classifier: Operating System :: OS Independent
Classifier: Programming Language :: Python :: 3.8
Classifier: Programming Language :: Python :: 3.9
Classifier: Programming Language :: Python :: 3.10
Classifier: Programming Language :: Python :: 3.11
Classifier: Typing :: Typed
Requires-Python: >=3.8.10
License-File: LICENSE
Requires-Dist: matplotlib (>=3.7.0)
Requires-Dist: numpy (>=1.24.2)
Requires-Dist: bidimensional (>=1.9.0)
